token_tools/__init__.py
token_tools/generator.py
django_token_tools-0.1.dist-info/LICENSE
django_token_tools-0.1.dist-info/METADATA
django_token_tools-0.1.dist-info/WHEEL
django_token_tools-0.1.dist-info/top_level.txt
django_token_tools-0.1.dist-info/RECORD
